images/claude-desktop-integration.png
images/cursor-integration.png
images/windsurf-integration.png
src/mcp_server_appwrite/__init__.py
src/mcp_server_appwrite/__main__.py
src/mcp_server_appwrite/server.py
src/mcp_server_appwrite/service.py
src/mcp_server_appwrite/tool_manager.py
orange1_mcp_server_appwrite-0.1.4.dist-info/METADATA
orange1_mcp_server_appwrite-0.1.4.dist-info/WHEEL
orange1_mcp_server_appwrite-0.1.4.dist-info/entry_points.txt
orange1_mcp_server_appwrite-0.1.4.dist-info/licenses/LICENSE
orange1_mcp_server_appwrite-0.1.4.dist-info/RECORD
