Metadata-Version: 2.4
Name: orange1-mcp-server-appwrite
Version: 0.1.4
Summary: MCP (Model Context Protocol) server for Appwrite
License-File: LICENSE
Requires-Python: >=3.12
Requires-Dist: appwrite>=9.0.3
Requires-Dist: docstring-parser>=0.16
Requires-Dist: mcp[cli]>=1.3.0
